coshed_flask/__init__.py
coshed_flask/authentication.py
coshed_flask/tools.py
coshed_flask/vial.py
coshed_flask-0.17.1.dist-info/COPYING
coshed_flask-0.17.1.dist-info/METADATA
coshed_flask-0.17.1.dist-info/WHEEL
coshed_flask-0.17.1.dist-info/RECORD
